{
"bank":{
"id":100
},
"bank.ReqEnterBank":{
"id":10001
},
"bank.ResEnterBank":{
"id":10002,
"resText":{
"0":"成功",
"1":"银行密码格式不正确",
"2":"银行密码不正确",
"3":"请先设置保险箱密码",
"4":"已经进入保险箱"
}
},
"bank.ReqSetBankPwd":{
"id":10003
},
"bank.ResSetBankPwd":{
"id":10004,
"resText":{
"0":"成功",
"1":"保险箱密码格式不正确"
}
},
"bank.ReqResetBankPwd":{
"id":10005
},
"bank.ResResetBankPwd":{
"id":10006,
"resText":{
"0":"成功",
"1":"银行密码格式不正确",
"2":"银行密码不正确"
}
},
"bank.ReqSaveGold":{
"id":10007
},
"bank.ResSaveGold":{
"id":10008,
"resText":{
"0":"成功",
"1":"金币不足"
}
},
"bank.ReqGetBankGold":{
"id":10009
},
"bank.ResGetBankGold":{
"id":10010,
"resText":{
"0":"成功",
"1":"金币不足",
"2":"金币金币不合法"
}
},
"bank.ReqGiftPresent":{
"id":10011
},
"bank.ResGiftPresent":{
"id":10012,
"resText":{
"0":"成功",
"1":"金币不足",
"2":"玩家不存在",
"3":"物品id不存在",
"4":"物品数量不正确",
"5":" 赠送物品数量超过单词上限"
}
},
"bank.ResTransferGold":{
"id":10013
},
"common":{
"id":200
},
"common.CommonMessage":{
"id":20001
},
"customer":{
"id":300
},
"customer.ReqCustomerMessage":{
"id":30001
},
"customer.ResCustomerMessage":{
"id":30002
},
"customer.ReqAddCustomerMessage":{
"id":30003
},
"customer.ResAddCustomerMessage":{
"id":30004,
"resText":{
"0":"成功",
"1":"失败 ",
"2":"消息内容不能为空"
}
},
"customer.ResReplyCustomerMessage":{
"id":30005
},
"customer.CustomerMessagePB":{
"id":30006
},
"dice":{
"id":400
},
"dice.ReqEnterDiceRoom":{
"id":40001
},
"dice.ResEnterDiceRoom":{
"id":40002,
"resText":{
"0":"成功",
"1":"已经进入房间了",
"2":"房间不存在",
"3":"房间已满"
}
},
"dice.ResEnterDiceRoomMsg":{
"id":40003
},
"dice.ReqExitDiceRoom":{
"id":40004
},
"dice.ResExitDiceRoom":{
"id":40005,
"resText":{
"0":"成功",
"1":"坐庄中不能退出房间"
}
},
"dice.ReqBetDice":{
"id":40006
},
"dice.ResBetDice":{
"id":40007,
"resText":{
"1":"当前阶段不是下注阶段",
"2":"金币不足，不能下注",
"3":"下注区域不存在",
"4":"下注金额不正确",
"5":"庄家不能下注",
"6":"下注筹码不正确",
"7":"庄家资金不够赔付，请稍后下注或者下注其他区域"
}
},
"dice.ResBetDiceMsg":{
"id":40008
},
"dice.ReqApplyBanker":{
"id":40009
},
"dice.ResApplyBanker":{
"id":40010,
"resText":{
"0":"成功",
"1":"已经是庄家",
"2":"金币不足",
"3":"申请庄家时人数超过上限",
"4":"不能重复申请",
"5":"申请上庄金币不足"
}
},
"dice.ResApplyBankerMsg":{
"id":40011
},
"dice.ReqExitBanker":{
"id":40012
},
"dice.ResExitBanker":{
"id":40013,
"resText":{
"1":"坐庄不能退出",
"2":"不在申请列表中"
}
},
"dice.ResBankerInfo":{
"id":40014
},
"dice.ResExitDiceRoomMsg":{
"id":40015
},
"dice.ResDiceStage":{
"id":40016
},
"dice.ApplicantInfoBP":{
"id":40017
},
"dice.BankerInfo":{
"id":40018
},
"dice.BetAreaInfo":{
"id":40019
},
"dice.ResDiceWinInfo":{
"id":40020
},
"dice.ReqDiceRank":{
"id":40021
},
"dice.ResDiceRank":{
"id":40022
},
"dice.ReqContinueBet":{
"id":40023
},
"dice.ResContinueBet":{
"id":40024,
"resText":{
"0":"成功",
"1":"没有历史数据",
"2":"下注金额不正确",
"3":"金币不足，不能下注",
"4":"当前阶段不是下注阶段",
"5":"庄家不能下注",
"6":"庄家资金不够赔付，请稍后下注或者下注其他区域"
}
},
"dice.ResContinueBetMsg":{
"id":40025
},
"dice.DiceSeatWinfo":{
"id":40026
},
"dice.DiceRank":{
"id":40027
},
"dice.ResSixSeatMsg":{
"id":40028
},
"dice.ReqBanker":{
"id":40029
},
"dice.ResBanker":{
"id":40030,
"resText":{
"0":"成功",
"1":"金币不足,抢庄失败",
"2":"抢庄金额不正确",
"3":"当前阶段不是抢庄阶段"
}
},
"dice.ResPlayerBankerMsg":{
"id":40031
},
"dice.PlayerBankerInfo":{
"id":40032
},
"email":{
"id":500
},
"email.ReqEmailList":{
"id":50001
},
"email.ResEmailList":{
"id":50002
},
"email.ReqReadEmail":{
"id":50003
},
"email.ResReadEmail":{
"id":50004,
"resText":{
"0":"成功",
"1":"邮件不存在"
}
},
"email.ReqDelEmail":{
"id":50005
},
"email.ResDelEmail":{
"id":50006,
"resText":{
"0":"成功",
"1":"邮件不存在"
}
},
"email.ReqDelAllEmail":{
"id":50007
},
"email.ResDelAllEmail":{
"id":50008,
"resText":{
"0":"成功"
}
},
"email.ResNewEmailMsg":{
"id":50009
},
"email.Email":{
"id":50010
},
"email.EmailInfo":{
"id":50011
},
"gobang":{
"id":600
},
"gobang.ReqcreateGobangRoom":{
"id":60001
},
"gobang.RescreateGobangRoom":{
"id":60002,
"resText":{
"0":"成功",
"1":"玩家已经创建房间",
"2":"人数已经满"
}
},
"gobang.ReqEnterGobangRoom":{
"id":60003
},
"gobang.ResEnterGobangRoom":{
"id":60004
},
"gobang.ReqReady":{
"id":60005
},
"gobang.ResReady":{
"id":60006,
"resText":{
"0":"成功",
"1":"已经准备"
}
},
"gobang.ResReadyMsg":{
"id":60007
},
"gobang.ReqCancel":{
"id":60008
},
"gobang.ResCancel":{
"id":60009,
"resText":{
"0":"成功"
}
},
"gobang.ResCancelMsg":{
"id":60010
},
"gobang.ReqMoveGobang":{
"id":60011
},
"gobang.ResMoveGobang":{
"id":60012,
"resText":{
"0":"成功",
"1":"当前位置已经有棋子",
"2":"位置不正确",
"3":"游戏没开始，不能落子",
"4":"不该你落子"
}
},
"gobang.ResMoveGobangMsg":{
"id":60013
},
"gobang.ReqPeace":{
"id":60014
},
"gobang.ResPeace":{
"id":60015,
"resText":{
"0":"成功"
}
},
"gobang.ResPeaceMsg":{
"id":60016
},
"gobang.ReqAnswerPeace":{
"id":60017
},
"gobang.ResAnswerPeace":{
"id":60018,
"resText":{
"0":"成功"
}
},
"gobang.ResPeaceResult":{
"id":60019
},
"gobang.ReqRetractChess":{
"id":60020
},
"gobang.ResRetractChess":{
"id":60021,
"resText":{
"0":"成功",
"1":"不能悔棋"
}
},
"gobang.ResRetractChessMsg":{
"id":60022
},
"gobang.ReqAnswerRetractChess":{
"id":60023
},
"gobang.ResAnswerRetractChess":{
"id":60024,
"resText":{
"0":"成功"
}
},
"gobang.ResRetractChessResult":{
"id":60025
},
"gobang.ReqGiveUp":{
"id":60026
},
"gobang.ResGiveUp":{
"id":60027,
"resText":{
"0":"成功"
}
},
"gobang.ReqExitRoom":{
"id":60028
},
"gobang.ResExitRoom":{
"id":60029,
"resText":{
"0":"成功",
"1":"游戏中不能退出"
}
},
"gobang.ResExitGobangRoomMsg":{
"id":60030
},
"gobang.ResGobangStage":{
"id":60031
},
"gobang.ResOtherEnterTable":{
"id":60032
},
"gobang.ResSeatColor":{
"id":60033
},
"gobang.GobangChess":{
"id":60034
},
"gobang.GobangSeatInfo":{
"id":60035
},
"gobang.GobangTableInfo":{
"id":60036
},
"gobang.ResGobangWinfo":{
"id":60037
},
"login":{
"id":700
},
"login.ReqLogin":{
"id":70001
},
"login.ReqTouristLogin":{
"id":70002
},
"login.ResLogin":{
"id":70003,
"resText":{
"0":"成功",
"1":"密码格式错误",
"2":"账号不存在"
}
},
"login.ReqTouristRegister":{
"id":70004
},
"login.ResTouristRegister":{
"id":70005,
"resText":{
"0":"成功"
}
},
"login.ReqLogout":{
"id":70006
},
"login.ResLogout":{
"id":70007,
"resText":{
"0":"正常退出",
"1":"同一个账号重复登录被T号退出",
"2":"玩家被冻结退出",
"3":"玩家被清除游戏退出",
"4":"停服玩家T出"
}
},
"login.ReqGetPhoneLoginCode":{
"id":70008
},
"login.ResGetPhoneLoginCode":{
"id":70009,
"resText":{
"0":"成功",
"1":"手机号码有误",
"2":"验证码已过期",
"3":"手机验证码失败超过最大次数4验证码不正确"
}
},
"login.ReqRegister":{
"id":70010
},
"login.ResRegister":{
"id":70011,
"resText":{
"0":"成功",
"1":"账号格式不正确",
"2":"账号重复"
}
},
"login.ResGameList":{
"id":70012
},
"login.ReqAgentList":{
"id":70013
},
"login.ResAgentList":{
"id":70014
},
"login.ReqPing":{
"id":70015
},
"login.ResPing":{
"id":70016
},
"login.Game":{
"id":70017
},
"login.Agent":{
"id":70018
},
"player":{
"id":800
},
"player.ResPlayerInfo":{
"id":80001
},
"player.ReqResetPwd":{
"id":80002
},
"player.ResResetPwd":{
"id":80003,
"resText":{
"0":"成功",
"1":"用户名不匹配",
"2":"密码格式错误3验证码已经过期",
"3":"验证码错误",
"4":"账号不存在"
}
},
"player.ReqModfiyNickName":{
"id":80004
},
"player.ResModfiyNickName":{
"id":80005,
"resText":{
"0":"成功",
"1":"昵称格式不正确",
"2":"昵称已经修改过"
}
},
"player.ReqBindingPhone":{
"id":80006
},
"player.ResBindingPhone":{
"id":80007,
"resText":{
"0":"成功",
"1":"手机码验证错误，绑定手机失败",
"2":"手机密码格式错误，绑定手机失败",
"3":"该用户已经绑定手机号,绑定手机失败"
}
},
"player.ReqModfiyIcon":{
"id":80008
},
"player.ResModfiyIcon":{
"id":80009,
"resText":{
"0":"成功",
"1":"头像不存在 "
}
},
"player.ReqLoadPlayerInfo":{
"id":80010
},
"player.ResLoadPlayerInfo":{
"id":80011,
"resText":{
"0":"成功",
"1":"玩家不存在 "
}
},
"player.ReqGiftList":{
"id":80012
},
"player.ResGiftList":{
"id":80013
},
"player.ReqModfiySignature":{
"id":80014
},
"player.ResModfiySignature":{
"id":80015,
"resText":{
"0":"成功",
"1":"个性签名不符合要求 "
}
},
"player.ResGoldChangeMsg":{
"id":80016
},
"player.PlayerPB":{
"id":80017
},
"player.Gift":{
"id":80018
},
"rank":{
"id":900
},
"rank.ReqRankList":{
"id":90001
},
"rank.ResRankList":{
"id":90002
},
"rank.RankInfo":{
"id":90003
},
"redpackage":{
"id":1000
},
"redpackage.ResRedPackageMsg":{
"id":100001
},
"redpackage.ReqOpenPackage":{
"id":100002
},
"redpackage.ResOpenPackage":{
"id":100003,
"resText":{
"0":"成功",
"1":"红包不存在",
"2":"红包已经领完",
"3":"红包已经过期"
}
},
"redpackage.ReqPackageInfo":{
"id":100004
},
"redpackage.ResPackageInfo":{
"id":100005,
"resText":{
"0":"成功",
"1":"红包不存在"
}
},
"redpackage.RedPackageInfo":{
"id":100006
},
"redpackage.PlayerRedPackage":{
"id":100007
}
}